napoleontoolbox/__init__.py
napoleontoolbox/analyzer/__init__.py
napoleontoolbox/analyzer/market.py
napoleontoolbox/backtest/__init__.py
napoleontoolbox/backtest/dynamic_plot_backtest.py
napoleontoolbox/backtest/plot_backtest.py
napoleontoolbox/backtest/plot_tools.py
napoleontoolbox/backtest/print_stats.py
napoleontoolbox/boosted_trees/__init__.py
napoleontoolbox/boosted_trees/roll_lightgbm.py
napoleontoolbox/connector/__init__.py
napoleontoolbox/connector/napoleon_connector.py
napoleontoolbox/display/__init__.py
napoleontoolbox/display/graph.py
napoleontoolbox/display/table.py
napoleontoolbox/neural_net/__init__.py
napoleontoolbox/neural_net/expanding_roll_multi_layer_perceptron.py
napoleontoolbox/neural_net/roll_aggregated_multi_neural_networks.py
napoleontoolbox/neural_net/roll_multi_layer_cnn.py
napoleontoolbox/neural_net/roll_multi_layer_lstm.py
napoleontoolbox/neural_net/roll_multi_layer_perceptron.py
napoleontoolbox/neural_net/roll_multi_neural_networks.py
napoleontoolbox/neural_net/roll_multi_roll_neural_networks.py
napoleontoolbox/neural_net/roll_neural_network.py
napoleontoolbox/parallel_run/__init__.py
napoleontoolbox/parallel_run/parallel_launcher.py
napoleontoolbox/parallel_run/parallel_saver.py
napoleontoolbox/rebalancing/__init__.py
napoleontoolbox/rebalancing/allocation.py
napoleontoolbox/rebalancing/rolling.py
napoleontoolbox/tools/__init__.py
napoleontoolbox/tools/analyze_tools.py
napoleontoolbox/tools/display.py
napoleontoolbox/tools/time_tools.py
napoleontoolbox/tools/utils.py
napoleontoolbox/utility/__init__.py
napoleontoolbox/utility/indicators.py
napoleontoolbox/utility/metrics.py
napoleontoolbox/utility/metrics_cy.cpython-37m-darwin.so
napoleontoolbox/utility/momentums.py
napoleontoolbox/utility/momentums_cy.cpython-37m-darwin.so
napoleontoolbox/utility/money_management.py
napoleontoolbox/utility/weights.py
napoleontoolbox-0.0.7.dist-info/METADATA
napoleontoolbox-0.0.7.dist-info/WHEEL
napoleontoolbox-0.0.7.dist-info/top_level.txt
napoleontoolbox-0.0.7.dist-info/RECORD
