Metadata-Version: 2.1
Name: napoleontoolbox
Version: 0.0.7
Summary: Dashboard for financial market data
Home-page: UNKNOWN
Author: Napoleon Group
Author-email: dsi@napoleonx.ai
License: MIT
Download-URL: https://github.com/stef564/napoleontoolbox/archive/0.0.7.tar.gz
Platform: UNKNOWN
Classifier: Development Status :: 4 - Beta
Classifier: Intended Audience :: Financial and Insurance Industry
Classifier: Intended Audience :: Science/Research
Classifier: License :: OSI Approved :: MIT License
Classifier: Operating System :: POSIX :: Linux
Classifier: Programming Language :: Python
Classifier: Programming Language :: Cython
Classifier: Programming Language :: Python :: 3
Classifier: Programming Language :: Python :: 3.5
Classifier: Programming Language :: Python :: 3.6
Classifier: Programming Language :: Python :: 3.7
Classifier: Topic :: Office/Business :: Financial
Classifier: Topic :: Scientific/Engineering :: Artificial Intelligence
Requires-Dist: Cython (>=0.29.0)
Requires-Dist: matplotlib (>=3.0.1)
Requires-Dist: numpy (>=1.15.3)
Requires-Dist: pandas (>=0.23.4)
Requires-Dist: scipy (>=1.2.0)
Requires-Dist: seaborn (>=0.9.0)
